erk/__init__.py
erk/__main__.py
erk/agent_docs/__init__.py
erk/agent_docs/models.py
erk/agent_docs/operations.py
erk/artifacts/__init__.py
erk/artifacts/artifact_health.py
erk/artifacts/detection.py
erk/artifacts/discovery.py
erk/artifacts/models.py
erk/artifacts/paths.py
erk/artifacts/staleness.py
erk/artifacts/state.py
erk/artifacts/sync.py
erk/cli/__init__.py
erk/cli/activation.py
erk/cli/alias.py
erk/cli/cli.py
erk/cli/config.py
erk/cli/constants.py
erk/cli/core.py
erk/cli/debug.py
erk/cli/ensure-conversion-tasks.md
erk/cli/ensure.py
erk/cli/github_parsing.py
erk/cli/graphite.py
erk/cli/graphite_command.py
erk/cli/help_formatter.py
erk/cli/output.py
erk/cli/script_output.py
erk/cli/shell_utils.py
erk/cli/subprocess_utils.py
erk/cli/uvx_detection.py
erk/cli/commands/__init__.py
erk/cli/commands/admin.py
erk/cli/commands/checkout_helpers.py
erk/cli/commands/codespace_executor.py
erk/cli/commands/completion.py
erk/cli/commands/completions.py
erk/cli/commands/config.py
erk/cli/commands/docker_executor.py
erk/cli/commands/doctor.py
erk/cli/commands/down.py
erk/cli/commands/implement.py
erk/cli/commands/implement_shared.py
erk/cli/commands/land_cmd.py
erk/cli/commands/log_cmd.py
erk/cli/commands/navigation_helpers.py
erk/cli/commands/objective_helpers.py
erk/cli/commands/prepare.py
erk/cli/commands/prepare_cwd_recovery.py
erk/cli/commands/status.py
erk/cli/commands/submit.py
erk/cli/commands/submit_helpers.py
erk/cli/commands/up.py
erk/cli/commands/artifact/__init__.py
erk/cli/commands/artifact/check.py
erk/cli/commands/artifact/group.py
erk/cli/commands/artifact/list_cmd.py
erk/cli/commands/artifact/show.py
erk/cli/commands/artifact/sync_cmd.py
erk/cli/commands/branch/__init__.py
erk/cli/commands/branch/checkout_cmd.py
erk/cli/commands/branch/create_cmd.py
erk/cli/commands/branch/delete_cmd.py
erk/cli/commands/branch/list_cmd.py
erk/cli/commands/cc/__init__.py
erk/cli/commands/cc/jsonl_cmd.py
erk/cli/commands/cc/session/AGENTS.md
erk-0.7.0.dist-info/METADATA
erk-0.7.0.dist-info/WHEEL
erk-0.7.0.dist-info/entry_points.txt
erk-0.7.0.dist-info/licenses/LICENSE.md
erk-0.7.0.dist-info/RECORD
