Metadata-Version: 2.4
Name: erk
Version: 0.7.0
Summary: Add your description here
Author-email: Dagster Labs <hello@dagsterlabs.com>
License-File: LICENSE.md
Requires-Python: >=3.11
Requires-Dist: click>=8.1.7
Requires-Dist: erk-shared
Requires-Dist: erk-statusline
Requires-Dist: packaging>=21.0
Requires-Dist: pathspec>=0.12.0
Requires-Dist: pydantic>=2.0
Requires-Dist: pyperclip>=1.8.2
Requires-Dist: python-frontmatter>=1.0.0
Requires-Dist: pyyaml>=6.0
Requires-Dist: rich>=13.0
Requires-Dist: textual-dev>=1.8.0
Requires-Dist: textual>=3.0.0
Requires-Dist: tomli-w>=1.0
Requires-Dist: tomli>=2.0
Requires-Dist: tomlkit>=0.12.0
